nulla/__init__.py
nulla/__main__.py
nulla/bootstrap.py
nulla/setup_assets.py
nulla/templates/Python 3.11.6.txt
nulla/templates/changelog.txt
nulla/templates/run_nulla.bat
nulla/templates/Whisper/Activate-Whisper.ps1
nulla/templates/assets/Nulla.ico
nulla/templates/assets/Nulla.png
nulla/templates/assets/bounce1.wav
nulla/templates/assets/defeat1.wav
nulla/templates/assets/dice_roll-1.wav
nulla/templates/assets/intro.wav
nulla/templates/assets/mic_off.png
nulla/templates/assets/mic_on.png
nulla/templates/assets/paper.png
nulla/templates/assets/rock.png
nulla/templates/assets/scissors.png
nulla/templates/assets/ttt_select.wav
nulla/templates/assets/victory1.wav
nulla/templates/assets/voice_ref-sample source.txt
nulla/templates/assets/voice_ref.wav
nulla/templates/scripts/nulla_chat.py
nulla/templates/scripts/nulla_game_bounce.py
nulla/templates/scripts/nulla_game_rps.py
nulla/templates/scripts/nulla_game_runner.py
nulla/templates/scripts/nulla_game_snake.py
nulla/templates/scripts/nulla_game_ttt.py
nulla/templates/scripts/nulla_hear.py
nulla/templates/scripts/nulla_list_game.py
nulla/templates/scripts/nulla_portrait.py
nulla/templates/scripts/nulla_window.py
nulla-0.0.7.dist-info/METADATA
nulla-0.0.7.dist-info/WHEEL
nulla-0.0.7.dist-info/entry_points.txt
nulla-0.0.7.dist-info/licenses/LICENSE
nulla-0.0.7.dist-info/RECORD
