Metadata-Version: 2.4
Name: nulla
Version: 0.0.7
Summary: Nulla: a local AI companion bootstrapper (Windows) with voice (Whisper ASR + XTTS v2 TTS), llama.cpp + OpenHermes GGUF, and built-in mini-games.
Project-URL: Homepage, https://github.com/Tsoxer/nulla
Project-URL: Source, https://github.com/Tsoxer/nulla
Project-URL: Issues, https://github.com/Tsoxer/nulla/issues
Author-email: Tsoxer <tsoxercontact@gmail.com>
License: ﻿MIT License
License-File: LICENSE
Keywords: ai companion,asr,coqui-tts,gguf,llama.cpp,minigame,nulla,openhermes,runner,snake,speech-to-text,text-to-speech,tts,whisper,xtts
Classifier: Development Status :: 3 - Alpha
Classifier: Environment :: Console
Classifier: Intended Audience :: Developers
Classifier: License :: OSI Approved :: MIT License
Classifier: Operating System :: Microsoft :: Windows
Classifier: Programming Language :: Python
Classifier: Programming Language :: Python :: 3
Classifier: Programming Language :: Python :: 3 :: Only
Classifier: Programming Language :: Python :: 3.11
Classifier: Topic :: Games/Entertainment
Classifier: Topic :: Multimedia :: Sound/Audio :: Speech
Classifier: Topic :: Scientific/Engineering :: Artificial Intelligence
Requires-Python: ==3.11.6
